yarnlog/__init__.py
yarnlog/main.py
yarnlog-0.2.1.dist-info/entry_points.txt
yarnlog-0.2.1.dist-info/WHEEL
yarnlog-0.2.1.dist-info/METADATA
yarnlog-0.2.1.dist-info/RECORD
