Metadata-Version: 2.1
Name: yarnlog
Version: 0.2.1
Summary: Download Apache Hadoop YARN log to your local machine.
Home-page: https://github.com/attomos/yarnlog
License: MIT
Keywords: yarn,hadoop,resource manager,log
Author: Nattaphoom Chaipreecha
Author-email: attomos@gmail.com
Requires-Python: >=3.8,<4.0
Classifier: License :: OSI Approved :: MIT License
Classifier: Programming Language :: Python :: 3
Classifier: Programming Language :: Python :: 3.8
Classifier: Programming Language :: Python :: 3.9
Requires-Dist: fire (>=0.3.1,<0.4.0)
Requires-Dist: hurry.filesize (>=0.9,<0.10)
Requires-Dist: pytest-cov (>=2.10.1,<3.0.0)
Requires-Dist: requests (>=2.25.0,<3.0.0)
Project-URL: Repository, https://github.com/attomos/yarnlog
